chanpy/__init__.py
chanpy/_buffers.py
chanpy/_channel.py
chanpy/core.py
chanpy/transducers.py
chanpy-0.0.2.dist-info/LICENSE
chanpy-0.0.2.dist-info/METADATA
chanpy-0.0.2.dist-info/WHEEL
chanpy-0.0.2.dist-info/top_level.txt
chanpy-0.0.2.dist-info/RECORD
