Metadata-Version: 2.1
Name: chanpy
Version: 0.0.2
Summary: A CSP library based on Clojure core.async
Home-page: https://github.com/JMagers/chanpy
Author: Jake Magers
Author-email: jmagers12@gmail.com
License: Apache License 2.0
Platform: UNKNOWN
Classifier: Programming Language :: Python :: 3
Classifier: License :: OSI Approved :: Apache Software License
Classifier: Operating System :: OS Independent
Requires-Python: >=3.7
